scidatacontainer/__init__.py
scidatacontainer/config.py
scidatacontainer/container.py
scidatacontainer/filebase.py
scidatacontainer/filehdf5.py
scidatacontainer/fileimage.py
scidatacontainer/filenumpy.py
scidatacontainer/jsonschema/SciDataContainer.content.1.0.0.schema.json
scidatacontainer/jsonschema/SciDataContainer.meta.1.0.0.schema.json
scidatacontainer/jsonschema/__init__.py
scidatacontainer/tests/__init__.py
scidatacontainer/tests/_abstract_container_test.py
scidatacontainer/tests/test_config.py
scidatacontainer/tests/test_download.py
scidatacontainer/tests/test_filebinary.py
scidatacontainer/tests/test_filehdf5.py
scidatacontainer/tests/test_fileimage.py
scidatacontainer/tests/test_filenumpy.py
scidatacontainer/tests/test_filetext.py
scidatacontainer/tests/test_json_schema.py
scidatacontainer/tests/test_multistep_container.py
scidatacontainer/tests/test_orcid.py
scidatacontainer/tests/test_register_class.py
scidatacontainer/tests/test_single_step_container.py
scidatacontainer/tests/test_static_container.py
scidatacontainer/tests/test_upload.py
scidatacontainer-1.1.9.dist-info/METADATA
scidatacontainer-1.1.9.dist-info/WHEEL
scidatacontainer-1.1.9.dist-info/licenses/LICENSE
scidatacontainer-1.1.9.dist-info/RECORD
