Metadata-Version: 2.4
Name: SciDataContainer
Version: 1.1.9
Summary: A container class for the storage of scientific data together with meta data.
Project-URL: Homepage, https://github.com/SciDataContainer/SciDataContainer
Project-URL: Documentation, https://scidatacontainer.readthedocs.io/en/latest
Project-URL: Bug Tracker, https://github.com/SciDataContainer/SciDataContainer/issues
Author-email: Reinhard Caspary <reinhard.caspary@phoenixd.uni-hannover.de>, Sven Kleinert <sven.kleinert@phoenixd.uni-hannover.de>
License: MIT License
License-File: LICENSE
Classifier: Intended Audience :: Science/Research
Classifier: License :: OSI Approved :: MIT License
Classifier: Operating System :: OS Independent
Classifier: Programming Language :: Python :: 3
Classifier: Topic :: Scientific/Engineering
Requires-Python: >=3.9
Requires-Dist: jsonschema[format-nongpl]
Requires-Dist: requests
